mcp_server_aws_resources/__init__.py
mcp_server_aws_resources/server.py
mseep_mcp_server_aws_resources-0.1.4.dist-info/METADATA
mseep_mcp_server_aws_resources-0.1.4.dist-info/WHEEL
mseep_mcp_server_aws_resources-0.1.4.dist-info/licenses/LICENSE
mseep_mcp_server_aws_resources-0.1.4.dist-info/RECORD
